setup.py
archicv/__init__.py
archicv/archi.py
archicv/archi32.py
archicv/coconut.py
archicv.egg-info/PKG-INFO
archicv.egg-info/SOURCES.txt
archicv.egg-info/dependency_links.txt
archicv.egg-info/top_level.txt
archicv/draw/__init__.py
archicv/draw/dxf_test_and_tutorial.py
archicv/draw/sdxf.py