Metadata-Version: 1.0
Name: archicv
Version: 0.0.2.1
Summary: Computer Vision on Landscape Architecture
Home-page: https://github.com/zhangxiansheng/-archi
Author: Zhang Yiwei
Author-email: Karl1991223@126.com
License: MIT License
Keywords: archicv,ArchiCV,archi,archiCV
Platform: any
